apertis/__init__.py
apertis/_base_client.py
apertis/_client.py
apertis/_constants.py
apertis/_exceptions.py
apertis/_helpers.py
apertis/_streaming.py
apertis/py.typed
apertis/resources/__init__.py
apertis/resources/embeddings.py
apertis/resources/messages.py
apertis/resources/models.py
apertis/resources/rerank.py
apertis/resources/responses.py
apertis/resources/chat/__init__.py
apertis/resources/chat/completions.py
apertis/types/__init__.py
apertis/types/chat.py
apertis/types/embeddings.py
apertis/types/messages.py
apertis/types/models.py
apertis/types/rerank.py
apertis/types/responses.py
apertis/types/shared.py
apertis-0.2.0.dist-info/METADATA
apertis-0.2.0.dist-info/WHEEL
apertis-0.2.0.dist-info/licenses/LICENSE
apertis-0.2.0.dist-info/RECORD
