Metadata-Version: 2.4
Name: apertis
Version: 0.2.0
Summary: Official Python SDK for Apertis AI API
Project-URL: Homepage, https://github.com/apertis-ai/python-sdk
Project-URL: Documentation, https://docs.apertis.ai
Project-URL: Repository, https://github.com/apertis-ai/python-sdk
Project-URL: Issues, https://github.com/apertis-ai/python-sdk/issues
Author: Apertis
License-Expression: Apache-2.0
License-File: LICENSE
Keywords: ai,apertis,chat,embeddings,llm,openai,sdk
Classifier: Development Status :: 4 - Beta
Classifier: Intended Audience :: Developers
Classifier: License :: OSI Approved :: Apache Software License
Classifier: Operating System :: OS Independent
Classifier: Programming Language :: Python :: 3
Classifier: Programming Language :: Python :: 3.9
Classifier: Programming Language :: Python :: 3.10
Classifier: Programming Language :: Python :: 3.11
Classifier: Programming Language :: Python :: 3.12
Classifier: Programming Language :: Python :: 3.13
Classifier: Topic :: Scientific/Engineering :: Artificial Intelligence
Classifier: Typing :: Typed
Requires-Python: >=3.9
Requires-Dist: httpx>=0.25.0
Requires-Dist: pydantic>=2.0.0
Requires-Dist: typing-extensions>=4.7.0
Provides-Extra: dev
Requires-Dist: mypy>=1.0.0; extra == 'dev'
Requires-Dist: pytest-asyncio>=0.21.0; extra == 'dev'
Requires-Dist: pytest>=7.0.0; extra == 'dev'
Requires-Dist: respx>=0.20.0; extra == 'dev'
Requires-Dist: ruff>=0.1.0; extra == 'dev'
